__init__.py
cli.py
constants.py
describe_file.py
embedding.py
bezzanlabs.gpt_docgen-0.1.0.dist-info/LICENSE
bezzanlabs.gpt_docgen-0.1.0.dist-info/METADATA
bezzanlabs.gpt_docgen-0.1.0.dist-info/WHEEL
bezzanlabs.gpt_docgen-0.1.0.dist-info/entry_points.txt
bezzanlabs.gpt_docgen-0.1.0.dist-info/top_level.txt
bezzanlabs.gpt_docgen-0.1.0.dist-info/RECORD
