Metadata-Version: 2.1
Name: bezzanlabs.gpt_docgen
Version: 0.1.0
Summary: CLI tool to generate project documentation from GPT models.
Author-email: Vitor Bezzan <vitor@bezzan.com>
Project-URL: Homepage, https://github.com/vitorbezzan/gpt_docgen
Project-URL: Bug Tracker, https://github.com/vitorbezzan/gpt_docgen
Requires-Python: ==3.11
License-File: LICENSE
Requires-Dist: chromadb ==0.5.3
Requires-Dist: pydantic ==2.7.4
Requires-Dist: typer ==0.12.3
Requires-Dist: openai ==1.35.7
Requires-Dist: python-dotenv
Requires-Dist: langchain ==0.2.6
Requires-Dist: langchain-community ==0.2.6
Requires-Dist: langchain-anthropic
Requires-Dist: langchain-cohere
Requires-Dist: langchain-openai
Requires-Dist: langchain-chroma ==0.1.2
Provides-Extra: dev
Requires-Dist: pre-commit ==3.7.1 ; extra == 'dev'
Requires-Dist: mypy ==1.10.1 ; extra == 'dev'
Requires-Dist: pytest ==8.2.2 ; extra == 'dev'
Requires-Dist: pytest-mock ; extra == 'dev'
Requires-Dist: pytest-cov ; extra == 'dev'
Requires-Dist: sphinx-autodoc-typehints ==2.2.2 ; extra == 'dev'
Requires-Dist: nbsphinx ==0.9.4 ; extra == 'dev'
Requires-Dist: sphinx ==7.3.7 ; extra == 'dev'
Requires-Dist: sphinx-copybutton ==0.5.2 ; extra == 'dev'
Requires-Dist: sphinx-rtd-theme ==2.0.0 ; extra == 'dev'
Requires-Dist: recommonmark ==0.7.1 ; extra == 'dev'
Requires-Dist: isort ==5.13.2 ; extra == 'dev'
Requires-Dist: pandas-stubs ==2.2.2.240603 ; extra == 'dev'
